pymycar/__init__.py
pymycar/files.py
pymycar/Cad/__init__.py
pymycar/Cad/animation.py
pymycar/Cad/geometric_forms.py
pymycar/Cad/Chassis/__init__.py
pymycar/Cad/Chassis/formula.py
pymycar/Cad/Chassis/tourist.py
pymycar/Cad/Suspension/double_whisbone.py
pymycar/Cad/Suspension/multilink.py
pymycar/Cad/Wheel/wheel.py
pymycar/Logger/__init__.py
pymycar/Logger/library_versions.py
pymycar/SuspensionKinematic/__init__.py
pymycar/SuspensionKinematic/double_whisbone.py
pymycar/SuspensionKinematic/functions.py
pymycar/SuspensionKinematic/multilink.py
pymycar/SuspensionKinematic/suspension_files.py
pymycar/Vehicle/__init__.py
pymycar/Vehicle/car.py
pymycar/Vehicle/chassis.py
pymycar/Vehicle/suspension.py
pymycar/Vehicle/wheel.py
pymycar/VerticalModels/__init__.py
pymycar/VerticalModels/exitations.py
pymycar/VerticalModels/models.py
pymycar-0.0.1.dist-info/METADATA
pymycar-0.0.1.dist-info/WHEEL
pymycar-0.0.1.dist-info/licenses/AUTHORS.rst
pymycar-0.0.1.dist-info/licenses/LICENSE
pymycar-0.0.1.dist-info/RECORD
