Metadata-Version: 2.4
Name: pymycar
Version: 0.0.1
Summary: pyMyCar: An Open-Source Framework for Vehicle Dynamics simulations
Project-URL: Homepage, https://github.com/CastillonMiguel/pymycar
Project-URL: Documentation, https://pymycar.readthedocs.io
Project-URL: Issues, https://github.com/CastillonMiguel/pymycar/issues
Author-email: Miguel Castillon <miguel.research@pm.me>
License: MIT License
License-File: AUTHORS.rst
License-File: LICENSE
Keywords: car,dynamic,suspension,vehicle
Classifier: License :: OSI Approved :: MIT License
Classifier: Operating System :: OS Independent
Classifier: Programming Language :: Python :: 3
Requires-Python: >=3.10
